{
  "italiano": "italiano",
  "english": "english",
  "italian": "italian",
  "italiana": "italiana",
  "inglese": "inglese",
  "ciao": "ciao",
  "buongiorno": "buongiorno",
  "salve": "salve",
  "buona sera": "buona sera",
  "ehi": "ehi",
  "buondì": "buondì",
  "eilà": "eilà",
  "votazione": "votazione",
  "requisiti": "requisiti",
  "test d'ingresso": "test d'ingresso",
  "iscrizione": "iscrizione",
  "diploma": "diploma",
  "iscrivermi": "iscrivermi",
  "informatica": "Informatica",
  "laurea triennale": "Laurea Triennale",
  "biologia": "Biologia",
  "economia": "Economia",
  "ingegneria meccanica": "Ingegneria Meccanica",
  "computer science": "Computer Science",
  "bachelor": "Bachelor",
  "biology": "Biology",
  "business administration": "Business Administration",
  "master": "Master",
  "physics": "Physics",
  "history": "History",
  "fisica": "Fisica",
  "magistrale": "Magistrale",
  "storia": "Storia",
  "chemistry": "Chemistry",
  "phd": "PhD",
  "mathematics": "Mathematics",
  "chimica": "Chimica",
  "dottorato": "Dottorato",
  "matematica": "Matematica",
  "arts": "Arts",
  "medicine": "Medicine",
  "medicina": "Medicina",
  "lettere": "Lettere",
  "mechanical engineering": "Mechanical Engineering",
  "lettere e filosofia": "Lettere e Filosofia",
  "arts and humanities": "Arts and Humanities",
  "economics": "Economics",
  "triennale": "Triennale",
  "101": "101",
  "102": "102",
  "103": "103",
  "104": "104",
  "105": "105",
  "mario rossi": "Mario Rossi",
  "john doe": "John Doe",
  "giulia bianchi": "Giulia Bianchi",
  "alice smith": "Alice Smith",
  "luca": "Luca",
  "robert brown": "Robert Brown",
  "luigi": "Luigi",
  "sarah": "Sarah",
  "master's degree": "Master's degree",
  "sarah connor": "Sarah Connor",
  "phd program": "PhD program",
  "laurea magistrale": "Laurea Magistrale",
  "master's": "Master's",
  "james bond": "James Bond",
  "alessandro": "Alessandro",
  "giuseppe verdi": "Giuseppe Verdi",
  "roberto baggio": "Roberto Baggio",
  "francesco": "Francesco",
  "biotechnology": "Biotechnology",
  "philosophy": "Philosophy",
  "undergraduate": "Undergraduate",
  "postgraduate": "Postgraduate",
  "giulia": "Giulia",
  "marco": "Marco",
  "engineering": "Engineering",
  "law": "Law",
  "giurisprudenza": "Giurisprudenza",
  "john.doe@example.com": "john.doe@example.com",
  "mario.rossi@gmail.com": "mario.rossi@gmail.com",
  "mario.rossi@example.com": "mario.rossi@example.com",
  "luigi99@libero.it": "luigi99@libero.it",
  "test.user@company.com": "test.user@company.com",
  "nome.cognome@universita.it": "nome.cognome@universita.it",
  "pippo@hotmail.it": "pippo@hotmail.it",
  "test@test.com": "test@test.com",
  "example@domain.org": "example@domain.org",
  "alex@email.com": "alex@email.com",
  "sara.connor@skynet.net": "sara.connor@skynet.net",
  "bond.james@mi6.uk": "bond.james@mi6.uk",
  "peppe@mail.it": "peppe@mail.it",
  "rossi@azienda.it": "rossi@azienda.it",
  "student@uni.edu": "student@uni.edu",
  "contact@me.com": "contact@me.com",
  "test.email@provider.com": "test.email@provider.com",
  "info@site.org": "info@site.org",
  "tasse": "tasse",
  "corsi di laurea": "corsi di laurea",
  "alloggi": "alloggi",
  "borse di studio": "borse di studio",
  "scadenze": "scadenze",
  "facoltà di ingegneria": "facoltà di ingegneria",
  "corsi": "corsi",
  "tuition fees": "tuition fees",
  "degree programs": "degree programs",
  "enrollment": "enrollment",
  "student housing": "student housing",
  "scholarships": "scholarships",
  "deadlines": "deadlines",
  "engineering faculty": "engineering faculty",
  "fees": "fees",
  "courses": "courses",
  "quanto costa": "quanto costa",
  "tasse universitarie": "tasse universitarie",
  "retta": "retta",
  "quanto si paga": "quanto si paga",
  "costo annuale": "costo annuale",
  "cost": "cost",
  "tuition fee": "tuition fee",
  "annual fee": "annual fee",
  "prices": "prices",
  "exams": "exams",
  "esami": "esami",
  "enrollment dates": "enrollment dates",
  "immatricolazione": "immatricolazione",
  "requirements": "requirements",
  "scholarship": "scholarship",
  "tuition": "tuition",
  "housing": "housing",
  "magistrali": "magistrali",
  "triennali": "triennali"
}